[
  {"County": "Merced County", "TotalCrimes": 8707, "MedianIncome": 64772},
  {"County": "Los Angeles County", "TotalCrimes": 308302, "MedianIncome": 83411},
  {"County": "Alameda County", "TotalCrimes": 80859, "MedianIncome": 122488},
  {"County": "Alpine County", "TotalCrimes": 36, "MedianIncome": 101125},
  {"County": "Amador County", "TotalCrimes": 641, "MedianIncome": 74853},
  {"County": "Butte County", "TotalCrimes": 5325, "MedianIncome": 66085},
  {"County": "Calaveras County", "TotalCrimes": 935, "MedianIncome": 77526},
  {"County": "Colusa County", "TotalCrimes": 430, "MedianIncome": 69619},
  {"County": "Contra Costa County", "TotalCrimes": 28993, "MedianIncome": 120020},
  {"County": "Del Norte County", "TotalCrimes": 838, "MedianIncome": 61149},
  {"County": "El Dorado County", "TotalCrimes": 2601, "MedianIncome": 99246},
  {"County": "Fresno County", "TotalCrimes": 35954, "MedianIncome": 67756},
  {"County": "Glenn County", "TotalCrimes": 425, "MedianIncome": 64033},
  {"County": "Humboldt County", "TotalCrimes": 3737, "MedianIncome": 57881},
  {"County": "Imperial County", "TotalCrimes": 3660, "MedianIncome": 53847},
  {"County": "Inyo County", "TotalCrimes": 472, "MedianIncome": 63417},
  {"County": "Kern County", "TotalCrimes": 36653, "MedianIncome": 63883},
  {"County": "Kings County", "TotalCrimes": 2775, "MedianIncome": 68540},
  {"County": "Lake County", "TotalCrimes": 1664, "MedianIncome": 56259},
  {"County": "Lassen County", "TotalCrimes": 596, "MedianIncome": 59515},
  {"County": "Marin County", "TotalCrimes": 5092, "MedianIncome": 142019},
  {"County": "Mariposa County", "TotalCrimes": 300, "MedianIncome": 60021},
  {"County": "Mendocino County", "TotalCrimes": 808, "MedianIncome": 61335},
  {"County": "Modoc County", "TotalCrimes": 135, "MedianIncome": 54962},
  {"County": "Mono County", "TotalCrimes": 205, "MedianIncome": 82038},
  {"County": "Monterey County", "TotalCrimes": 8341, "MedianIncome": 91043},
  {"County": "Napa County", "TotalCrimes": 2516, "MedianIncome": 105809},
  {"County": "Nevada County", "TotalCrimes": 1533, "MedianIncome": 43421},
  {"County": "Orange County", "TotalCrimes": 69165, "MedianIncome": 109361},
  {"County": "Placer County", "TotalCrimes": 6729, "MedianIncome": 109375},
  {"County": "Plumas County", "TotalCrimes": 446, "MedianIncome": 67885},
  {"County": "Riverside County", "TotalCrimes": 64891, "MedianIncome": 84505},
  {"County": "Sacramento County", "TotalCrimes": 46477, "MedianIncome": 84010},
  {"County": "San Benito County", "TotalCrimes": 732, "MedianIncome": 104451},
  {"County": "San Bernardino County", "TotalCrimes": 56531, "MedianIncome": 77423},
  {"County": "San Diego County", "TotalCrimes": 65660, "MedianIncome": 96974},
  {"County": "San Francisco County", "TotalCrimes": 54220, "MedianIncome": 136689},
  {"County": "San Joaquin County", "TotalCrimes": 21057, "MedianIncome": 82837},
  {"County": "San Luis Obispo County", "TotalCrimes": 6460, "MedianIncome": 90158},
  {"County": "San Mateo County", "TotalCrimes": 17941, "MedianIncome": 149907},
  {"County": "Santa Barbara County", "TotalCrimes": 10540, "MedianIncome": 92332},
  {"County": "Santa Clara County", "TotalCrimes": 55690, "MedianIncome": 153792},
  {"County": "Santa Cruz County", "TotalCrimes": 6510, "MedianIncome": 51885},
  {"County": "Shasta County", "TotalCrimes": 695, "MedianIncome": 68347},
  {"County": "Sierra County", "TotalCrimes": 31, "MedianIncome": 61108},
  {"County": "Siskiyou County", "TotalCrimes": 1058, "MedianIncome": 53898},
  {"County": "Solano County", "TotalCrimes": 14498, "MedianIncome": 97037},
  {"County": "Sonoma County", "TotalCrimes": 7772, "MedianIncome": 99266},
  {"County": "Stanislaus County", "TotalCrimes": 14457, "MedianIncome": 74872},
  {"County": "Sutter County", "TotalCrimes": 2845, "MedianIncome": 72654},
  {"County": "Tehama County", "TotalCrimes": 1865, "MedianIncome": 59029},
  {"County": "Trinity County", "TotalCrimes": 334, "MedianIncome": 47317},
  {"County": "Tulare County", "TotalCrimes": 12154, "MedianIncome": 64474},
  {"County": "Tuolumne County", "TotalCrimes": 1116, "MedianIncome": 70432},
  {"County": "Ventura County", "TotalCrimes": 12883, "MedianIncome": 102141},
  {"County": "Yolo County", "TotalCrimes": 5859, "MedianIncome": 85097},
  {"County": "Yuba County", "TotalCrimes": 1527, "MedianIncome": 66693}
]